Metadata-Version: 1.0
Name: flask-geokit
Version: 0.1.6
Summary: Geocoding toolkit
Home-page: https://github.com/bluemoon/flask-geokit
Author: Alex Toney
Author-email: toneyalex@gmail.com
License: BSD
Platform: any
Classifier: Environment :: Web Environment
Classifier: Intended Audience :: Developers
Classifier: License :: OSI Approved :: BSD License
Classifier: Operating System :: OS Independent
Classifier: Programming Language :: Python
Classifier: Topic :: Internet :: WWW/HTTP :: Dynamic Content
Classifier: Topic :: Software Development :: Libraries :: Python Modules
